anime_downloader/__init__.py
anime_downloader/__main__.py
anime_downloader/main.py
anime_downloader/api/__init__.py
anime_downloader/api/client.py
anime_downloader/api/downloader.py
anime_downloader/cli/__init__.py
anime_downloader/cli/commands.py
anime_downloader/cli/completions.py
anime_downloader/cli/interactive.py
anime_downloader/core/__init__.py
anime_downloader/core/exceptions.py
anime_downloader/core/signal_handler.py
anime_downloader/gui/__init__.py
anime_downloader/gui/main_window.py
anime_downloader/gui/workers.py
anime_downloader/gui/dialogs/__init__.py
anime_downloader/gui/dialogs/settings_dialog.py
anime_downloader/models/__init__.py
anime_downloader/models/models.py
anime_downloader/services/__init__.py
anime_downloader/services/cache_service.py
anime_downloader/services/daemon_service.py
anime_downloader/utils/__init__.py
anime_downloader/utils/config_manager.py
anime_downloader/utils/console.py
anime_downloader/utils/constants.py
anime_downloader/utils/helper.py
anime_downloader/utils/logger.py
animepahe_dl-5.8.1.dist-info/METADATA
animepahe_dl-5.8.1.dist-info/WHEEL
animepahe_dl-5.8.1.dist-info/entry_points.txt
animepahe_dl-5.8.1.dist-info/licenses/LICENSE
animepahe_dl-5.8.1.dist-info/RECORD
