Metadata-Version: 2.4
Name: animepahe-dl
Version: 5.8.1
Summary: A feature-rich anime downloader with CLI and GUI support
Project-URL: Homepage, https://github.com/ayushjaipuriyar/animepahe-dl
Project-URL: Bug Tracker, https://github.com/ayushjaipuriyar/animepahe-dl/issues
Project-URL: Documentation, https://github.com/ayushjaipuriyar/animepahe-dl#readme
Project-URL: Source Code, https://github.com/ayushjaipuriyar/animepahe-dl
Project-URL: Changelog, https://github.com/ayushjaipuriyar/animepahe-dl/blob/main/CHANGELOG.md
Author-email: Ayush <ayushjaipuriyar21@gmail.com>
License: MIT
License-File: LICENSE
Keywords: anime,animepahe,downloader,streaming,video
Classifier: Development Status :: 5 - Production/Stable
Classifier: Intended Audience :: End Users/Desktop
Classifier: License :: OSI Approved :: MIT License
Classifier: Operating System :: OS Independent
Classifier: Programming Language :: Python :: 3
Classifier: Programming Language :: Python :: 3.8
Classifier: Programming Language :: Python :: 3.9
Classifier: Programming Language :: Python :: 3.10
Classifier: Programming Language :: Python :: 3.11
Classifier: Programming Language :: Python :: 3.12
Classifier: Topic :: Internet :: WWW/HTTP
Classifier: Topic :: Multimedia :: Video
Requires-Python: >=3.8
Requires-Dist: beautifulsoup4>=4.14.3
Requires-Dist: loguru>=0.7.0
Requires-Dist: platformdirs>=4.0.0
Requires-Dist: plyer>=2.1.0
Requires-Dist: pycryptodome>=3.19.0
Requires-Dist: pyfzf>=0.3.0
Requires-Dist: pyqt6>=6.6.0
Requires-Dist: questionary>=2.0.0
Requires-Dist: rich>=13.0.0
Requires-Dist: tqdm>=4.66.0
Requires-Dist: typer>=0.9.0
Requires-Dist: urllib3<2.5.0,>=2.0.0; python_version < '3.9'
Requires-Dist: urllib3>=2.6.1; python_version >= '3.9'
Provides-Extra: dev
Requires-Dist: bandit>=1.7.5; extra == 'dev'
Requires-Dist: black>=23.0.0; extra == 'dev'
Requires-Dist: isort>=5.12.0; extra == 'dev'
Requires-Dist: mypy>=1.7.0; extra == 'dev'
Requires-Dist: pytest-asyncio>=0.21.0; extra == 'dev'
Requires-Dist: pytest-cov>=4.1.0; extra == 'dev'
Requires-Dist: pytest-mock>=3.12.0; extra == 'dev'
Requires-Dist: pytest>=7.4.0; extra == 'dev'
Requires-Dist: python-semantic-release>=10.5.2; extra == 'dev'
Requires-Dist: ruff>=0.1.0; extra == 'dev'
Requires-Dist: safety>=2.3.0; extra == 'dev'
Requires-Dist: twine<6.2.0,>=6.1.0; (python_version < '3.9') and extra == 'dev'
Requires-Dist: twine>=6.2.0; (python_version >= '3.9') and extra == 'dev'
